simplebot_corpse/__init__.py
simplebot_corpse/orm.py
simplebot_corpse-1.0.0.dist-info/LICENSE
simplebot_corpse-1.0.0.dist-info/METADATA
simplebot_corpse-1.0.0.dist-info/WHEEL
simplebot_corpse-1.0.0.dist-info/entry_points.txt
simplebot_corpse-1.0.0.dist-info/top_level.txt
simplebot_corpse-1.0.0.dist-info/RECORD
